mycoai/__init__.py
mycoai/evaluate.py
mycoai/plotter.py
mycoai/utils.py
mycoai/data/__init__.py
mycoai/data/data.py
mycoai/data/encoders.py
mycoai/data/tensor_data.py
mycoai/modules/__init__.py
mycoai/modules/cnns.py
mycoai/modules/output_heads.py
mycoai/modules/seq_class_network.py
mycoai/modules/transformers.py
mycoai/scripts/classify.py
mycoai/scripts/evaluate.py
mycoai/scripts/map.py
mycoai/scripts/train.py
mycoai/train/__init__.py
mycoai/train/label_smoothing.py
mycoai/train/loss.py
mycoai/train/masked_language_modeling.py
mycoai/train/seq_class_trainer.py
mycoai/train/weight_schedules.py
mycoai_its-0.0.5.dist-info/METADATA
mycoai_its-0.0.5.dist-info/WHEEL
mycoai_its-0.0.5.dist-info/entry_points.txt
mycoai_its-0.0.5.dist-info/licenses/LICENSE
mycoai_its-0.0.5.dist-info/RECORD
