Metadata-Version: 2.3
Name: mycoai-its
Version: 0.0.5
Summary: (Fungal ITS) DNA barcode classification with neural networks.
Project-URL: Homepage, https://github.com/MycoAI/MycoAI
Project-URL: Issues, https://github.com/MycoAI/MycoAI/issues
Author-email: Luuk Romeijn <luukromeijn@hotmail.nl>
License-File: LICENSE
Classifier: License :: OSI Approved :: MIT License
Classifier: Operating System :: OS Independent
Classifier: Programming Language :: Python :: 3
Requires-Python: >=3.8
Requires-Dist: biopython>=1.79
Requires-Dist: matplotlib
Requires-Dist: numpy
Requires-Dist: pandas
Requires-Dist: plotly~=5.17.0
Requires-Dist: scikit-learn~=1.3.0
Requires-Dist: scipy
Requires-Dist: sentencepiece~=0.1.99
Requires-Dist: torch>=1.12.0
Requires-Dist: tqdm
Requires-Dist: wandb~=0.15.12
